README.rst
setup.py
dist/django-simple-events-0.1.tar.gz
dist/django-simple-events-0.2.tar.gz
dist/django-simple-events-0.3.tar.gz
dist/django-simple-events-0.4.tar.gz
dist/django-simple-events-0.5.tar.gz
dist/django-simple-events-1.0.tar.gz
django_simple_events.egg-info/PKG-INFO
django_simple_events.egg-info/SOURCES.txt
django_simple_events.egg-info/dependency_links.txt
django_simple_events.egg-info/requires.txt
django_simple_events.egg-info/top_level.txt
events/__init__.py
events/admin.py
events/forms.py
events/models.py
events/locale/es/LC_MESSAGES/django.mo
events/locale/es/LC_MESSAGES/django.po
events/locale/eu/LC_MESSAGES/django.mo
events/locale/eu/LC_MESSAGES/django.po
events/management/__init__.py
events/management/commands/__init__.py
events/management/commands/update_occurrences_set.py