Metadata-Version: 1.0
Name: django-simple-events
Version: 1.2
Summary: UNKNOWN
Home-page: http://unaizalakain.info/blog/django-simple-events/
Author: Unai Zalakain
Author-email: contact@unaizalakain.info
License: GPLv3
Download-URL: http://svn.unaizalakain.info/django-simple-events/
Keywords: events occurrences daily weekly montly yearly repetitions
Platform: UNKNOWN
Classifier: Development Status :: 5 - Production/Stable
Classifier: Framework :: Django
Classifier: Intended Audience :: Developers
Classifier: License :: OSI Approved :: GNU General Public License (GPL)
Classifier: Natural Language :: English
Classifier: Programming Language :: Python :: 2.6
